setup.py
app_container/__init__.py
app_container/lib.py
silk_config.egg-info/PKG-INFO
silk_config.egg-info/SOURCES.txt
silk_config.egg-info/dependency_links.txt
silk_config.egg-info/requires.txt
silk_config.egg-info/top_level.txt
silk_extras/__init__.py
silk_extras/django_membrane.py