Metadata-Version: 1.0
Name: silk-config
Version: 0.3.5
Summary: Small package for reading and returning the configuration of a Silk-configured site
Home-page: http://bits.btubbs.com/silk-config
Author: Brent Tubbs
Author-email: brent.tubbs@gmail.com
License: LICENSE.txt
Platform: UNKNOWN
